CHANGELOG.rst
LICENSE
MANIFEST.in
README.rst
setup.py
src/collective/__init__.py
src/collective.argv0spy.egg-info/PKG-INFO
src/collective.argv0spy.egg-info/SOURCES.txt
src/collective.argv0spy.egg-info/dependency_links.txt
src/collective.argv0spy.egg-info/namespace_packages.txt
src/collective.argv0spy.egg-info/not-zip-safe
src/collective.argv0spy.egg-info/requires.txt
src/collective.argv0spy.egg-info/top_level.txt
src/collective/argv0spy/__init__.py
src/collective/argv0spy/configure.zcml