Metadata-Version: 1.1
Name: collective.argv0spy
Version: 0.1.3
Summary: Change process title to show current urls being processed
Home-page: https://github.com/collective/collective.argv0spy
Author: Patrick Gerken
Author-email: gerken@patrick-gerken.de
License: MIT
Platform: UNKNOWN
Classifier: Programming Language :: Python
